fuzzyexact/__init__.py
fuzzyexact/clean_address.py
fuzzyexact/fuzzyexact.py
fuzzyexact/remove_punctuation.py
fuzzyexact-1.0.0.dist-info/LICENSE
fuzzyexact-1.0.0.dist-info/METADATA
fuzzyexact-1.0.0.dist-info/WHEEL
fuzzyexact-1.0.0.dist-info/top_level.txt
fuzzyexact-1.0.0.dist-info/RECORD
