Metadata-Version: 2.1
Name: fuzzyexact
Version: 1.0.0
Summary: Perform fuzzy matching against two pandas dataframes with optional exact matches
Home-page: https://github.com/eric-tomasi/fuzzyexact
Author: Eric Tomasi
Author-email: etomasi2323@gmail.com
License: MIT
Keywords: fuzzy,fuzzymatch,fuzzyexact,fuzzy block
Platform: UNKNOWN
Requires-Dist: pandas
Requires-Dist: fuzzywuzzy
